[
    {
        "name":"Sifat Hasan",
        "designation":"Agen Founder",
        "testimony":"Lorem ipsum, dolor sit amet consectetur adipisicing elit. Molestias aut. debitis nisi nostrum.",
        "image":"images/jack.jpg"
    },
    {
        "name":"Sifat Hasan",
        "designation":"Agen Founder",
        "testimony":"Lorem ipsum, dolor sit amet consectetur adipisicing elit. Molestias aut. debitis nisi nostrum.",
        "image":"images/sarah.jpg"
    },
    {
        "name":"Sifat Hasan",
        "designation":"Agen Founder",
        "testimony":"Lorem ipsum, dolor sit amet consectetur adipisicing elit. Molestias aut. debitis nisi nostrum.",
        "image":"images/jack.jpg"
    }
]